README.md
setup.py
aws_cloud_trail_events_schema/__init__.py
aws_cloud_trail_events_schema/cli.py
aws_cloudtrail_events_schema.egg-info/PKG-INFO
aws_cloudtrail_events_schema.egg-info/SOURCES.txt
aws_cloudtrail_events_schema.egg-info/dependency_links.txt
aws_cloudtrail_events_schema.egg-info/entry_points.txt
aws_cloudtrail_events_schema.egg-info/requires.txt
aws_cloudtrail_events_schema.egg-info/top_level.txt