Metadata-Version: 2.1
Name: aws-cloudtrail-events-schema
Version: 0.0.6
Summary: Utility to discover AWS CloudTrail events pushed into S3
Home-page: https://github.com/eamonnfaherty/aws-cloudtrail-events-schema
Author: Eamonn Faherty
Author-email: python-packages@designandsolve.co.uk
License: UNKNOWN
Platform: UNKNOWN
Classifier: Programming Language :: Python :: 3
Classifier: License :: OSI Approved :: MIT License
Classifier: Operating System :: OS Independent
